{
  "countryData": {
    "name": "Afghanistan",
    "officialName": "The Afghanistan",
    "capital": "Kabul.mw-parser-output .geo-default,.mw-parser-output .geo-dms,.mw-parser-output .geo-dec{display:inline}.mw-parser-output .geo-nondefault,.mw-parser-output .geo-multi-punct,.mw-parser-output .geo-inline-hidden{display:none}.mw-parser-output .longitude,.mw-parser-output .latitude{white-space:nowrap}34°31′N 69°11′E / 34.517°N 69.183°E / 34.517; 69.183",
    "population": "42%",
    "area": "652,864",
    "governmentType": "Unitary totalitarian theocratic Islamic emirate",
    "currency": "Afghani",
    "gdp": "2023"
  },
  "leadership": {
    "headOfState": {
      "name": "9 June 1926",
      "position": "Head of State"
    },
    "headOfGovernment": {
      "name": "Hasan Akhund",
      "position": "Head of Government"
    }
  }
}