{
  "countryData": {
    "name": "Micronesia (Federated States of)",
    "officialName": "The Micronesia (Federated States of)",
    "capital": "Palikir.mw-parser-output .geo-default,.mw-parser-output .geo-dms,.mw-parser-output .geo-dec{display:inline}.mw-parser-output .geo-nondefault,.mw-parser-output .geo-multi-punct,.mw-parser-output .geo-inline-hidden{display:none}.mw-parser-output .longitude,.mw-parser-output .latitude{white-space:nowrap}6°55′N 158°11′E / 6.917°N 158.183°E / 6.917; 158.183",
    "population": "104,468",
    "area": "702",
    "governmentType": "Federal assembly-independent republic under a non-partisan democracy",
    "currency": "United States dollar",
    "gdp": "2025"
  },
  "leadership": {
    "headOfState": {
      "name": "Wesley Simina",
      "position": "Head of State"
    }
  }
}